repypi/__init__.py
repypi/main.py
repypi-1.1.6.dist-info/METADATA
repypi-1.1.6.dist-info/WHEEL
repypi-1.1.6.dist-info/entry_points.txt
repypi-1.1.6.dist-info/top_level.txt
repypi-1.1.6.dist-info/RECORD
