Metadata-Version: 2.1
Name: repypi
Version: 1.1.6
Summary: This is a short description
Home-page: https://link-to-project-webpage.com
Author: you
Author-email: you@gmail.com
Classifier: Programming Language :: Python :: 3
Requires-Python: >=3.6
Requires-Dist: python-dateutil (~=2.8.2)
Requires-Dist: requirements-parser (~=0.5.0)
Requires-Dist: natsort (~=8.2.0)
Requires-Dist: requests (~=2.28.1)
